streamlit_pandas_profiling/__init__.py
streamlit_pandas_profiling/version.py
streamlit_pandas_profiling/frontend/build/asset-manifest.json
streamlit_pandas_profiling/frontend/build/index.html
streamlit_pandas_profiling/frontend/build/static/js/2.1bdc3fbc.chunk.js
streamlit_pandas_profiling/frontend/build/static/js/2.1bdc3fbc.chunk.js.LICENSE.txt
streamlit_pandas_profiling/frontend/build/static/js/2.d1a0ea7c.chunk.js
streamlit_pandas_profiling/frontend/build/static/js/2.d1a0ea7c.chunk.js.LICENSE.txt
streamlit_pandas_profiling/frontend/build/static/js/main.55b53955.chunk.js
streamlit_pandas_profiling/frontend/build/static/js/main.c96126f5.chunk.js
streamlit_pandas_profiling/frontend/build/static/js/runtime-main.074bebed.js
streamlit_pandas_profiling/frontend/build/static/js/runtime-main.aaad0ea0.js
streamlit_pandas_profiling-0.1.3.dist-info/LICENSE
streamlit_pandas_profiling-0.1.3.dist-info/METADATA
streamlit_pandas_profiling-0.1.3.dist-info/WHEEL
streamlit_pandas_profiling-0.1.3.dist-info/top_level.txt
streamlit_pandas_profiling-0.1.3.dist-info/RECORD
