Metadata-Version: 2.1
Name: streamlit-pandas-profiling
Version: 0.1.3
Summary: Pandas Profiling component for Streamlit.
Home-page: https://share.streamlit.io/okld/streamlit-gallery/main?p=pandas-profiling
Author: okld
License: MIT
Platform: UNKNOWN
Requires-Python: >=3.6
License-File: LICENSE
